worldalphabets/__init__.py
worldalphabets/helpers.py
worldalphabets/data/index.json
worldalphabets/data/alphabets/af.json
worldalphabets/data/alphabets/ak.json
worldalphabets/data/alphabets/am.json
worldalphabets/data/alphabets/ar.json
worldalphabets/data/alphabets/ast.json
worldalphabets/data/alphabets/az.json
worldalphabets/data/alphabets/ba.json
worldalphabets/data/alphabets/ban.json
worldalphabets/data/alphabets/bax.json
worldalphabets/data/alphabets/be.json
worldalphabets/data/alphabets/bg.json
worldalphabets/data/alphabets/bku.json
worldalphabets/data/alphabets/bm.json
worldalphabets/data/alphabets/bn.json
worldalphabets/data/alphabets/bo.json
worldalphabets/data/alphabets/bug.json
worldalphabets/data/alphabets/bya.json
worldalphabets/data/alphabets/ca.json
worldalphabets/data/alphabets/ceb.json
worldalphabets/data/alphabets/chr.json
worldalphabets/data/alphabets/ckb.json
worldalphabets/data/alphabets/cop.json
worldalphabets/data/alphabets/cs.json
worldalphabets/data/alphabets/cv.json
worldalphabets/data/alphabets/da.json
worldalphabets/data/alphabets/de.json
worldalphabets/data/alphabets/dz.json
worldalphabets/data/alphabets/el.json
worldalphabets/data/alphabets/en.json
worldalphabets/data/alphabets/eo.json
worldalphabets/data/alphabets/es.json
worldalphabets/data/alphabets/et.json
worldalphabets/data/alphabets/eu.json
worldalphabets/data/alphabets/fa.json
worldalphabets/data/alphabets/fi.json
worldalphabets/data/alphabets/fo.json
worldalphabets/data/alphabets/fr.json
worldalphabets/data/alphabets/fur.json
worldalphabets/data/alphabets/ga.json
worldalphabets/data/alphabets/gd.json
worldalphabets/data/alphabets/gez.json
worldalphabets/data/alphabets/gl.json
worldalphabets/data/alphabets/gu.json
worldalphabets/data/alphabets/gv.json
worldalphabets/data/alphabets/haw.json
worldalphabets/data/alphabets/he.json
worldalphabets/data/alphabets/hi.json
worldalphabets/data/alphabets/hnn.json
worldalphabets/data/alphabets/ht.json
worldalphabets/data/alphabets/hu.json
worldalphabets-0.1.0.dist-info/licenses/LICENSE
worldalphabets-0.1.0.dist-info/METADATA
worldalphabets-0.1.0.dist-info/WHEEL
worldalphabets-0.1.0.dist-info/top_level.txt
worldalphabets-0.1.0.dist-info/RECORD
