Metadata-Version: 2.4
Name: worldalphabets
Version: 0.1.0
Requires-Python: >=3.11
License-File: LICENSE
Requires-Dist: langcodes>=3.3.0
Requires-Dist: language-data>=1.1.0
Provides-Extra: dev
Requires-Dist: pytest>=8.0.0; extra == "dev"
Requires-Dist: ruff>=0.1.0; extra == "dev"
Requires-Dist: mypy>=1.0.0; extra == "dev"
Requires-Dist: build>=0.10.0; extra == "dev"
Requires-Dist: requests>=2.31.0; extra == "dev"
Requires-Dist: beautifulsoup4>=4.12.3; extra == "dev"
Requires-Dist: types-requests; extra == "dev"
Requires-Dist: types-beautifulsoup4; extra == "dev"
Dynamic: license-file
